{
  ".DS_Store": 1480093483000,
  "404.md": 1482613643000,
  "favicon.ico": 1482699622000,
  "index.md": 1482699622000,
  "dissertation/index.md": 1455464726000,
  "datasets/index.md": 1482705310000,
  "datasets/centro-nacional-de-memoria-historica/index.md": 1482699622000,
  "datasets/ingeominas/index.md": 1482699622000,
  "datasets/monitor/index.md": 1482699622000,
  "datasets/pulse/index.md": 1482699622000,
  "datasets/noche-y-niebla/index.md": 1482699622000,
  "js/.DS_Store": 1461507313000,
  "js/Notations.js": 1482699622000,
  "js/site-scripts.js": 1482699622000,
  "js/vendor/d3-3.5.6.min.js": 1455465050000,
  "js/vendor/jquery-2.1.4.min.js": 1455465050000,
  "js/vendor/jquery-ui-1.11.4.min.js": 1455465050000,
  "js/vendor/moment.js": 1455465050000,
  "fonts/.DS_Store": 1462419232000,
  "fonts/Inconsolata/Inconsolata-700.eot": 1482699622000,
  "fonts/Inconsolata/Inconsolata-700.svg": 1482699622000,
  "fonts/Inconsolata/Inconsolata-700.ttf": 1482699622000,
  "fonts/Inconsolata/Inconsolata-700.woff": 1482699622000,
  "fonts/Inconsolata/Inconsolata-700.woff2": 1482699622000,
  "fonts/Inconsolata/Inconsolata-regular.eot": 1482699622000,
  "fonts/Inconsolata/Inconsolata-regular.svg": 1482699622000,
  "fonts/Inconsolata/Inconsolata-regular.ttf": 1482699622000,
  "fonts/Inconsolata/Inconsolata-regular.woff": 1482699622000,
  "fonts/Inconsolata/Inconsolata-regular.woff2": 1482699622000,
  "fonts/Inconsolata/LICENSE.txt": 1482699622000,
  "fonts/geo/Geo-regular.eot": 1482699622000,
  "fonts/geo/Geo-regular.svg": 1482699622000,
  "fonts/geo/Geo-regular.ttf": 1482699622000,
  "fonts/geo/Geo-regular.woff": 1482699622000,
  "fonts/geo/Geo-regular.woff2": 1482699622000,
  "fonts/geo/LICENSE.txt": 1482699622000,
  "fonts/volkron/LICENSE.txt": 1482699622000,
  "fonts/volkron/Vollkorn-italic.eot": 1482699622000,
  "fonts/volkron/Vollkorn-italic.svg": 1482699622000,
  "fonts/volkron/Vollkorn-italic.ttf": 1482699622000,
  "fonts/volkron/Vollkorn-italic.woff": 1482699622000,
  "fonts/volkron/Vollkorn-italic.woff2": 1482699622000,
  "fonts/volkron/Vollkorn-regular.eot": 1482699622000,
  "fonts/volkron/Vollkorn-regular.svg": 1482699622000,
  "fonts/volkron/Vollkorn-regular.ttf": 1482699622000,
  "fonts/volkron/Vollkorn-regular.woff": 1482699622000,
  "fonts/volkron/Vollkorn-regular.woff2": 1482699622000,
  "fonts/warnes/LICENSE.txt": 1482699622000,
  "fonts/warnes/Warnes-regular.eot": 1482699622000,
  "fonts/warnes/Warnes-regular.svg": 1482699622000,
  "fonts/warnes/Warnes-regular.ttf": 1482699622000,
  "fonts/warnes/Warnes-regular.woff": 1482699622000,
  "fonts/warnes/Warnes-regular.woff2": 1482699622000,
  "scss/.DS_Store": 1461507313000,
  "scss/style.scss": 1455464726000,
  "scss/lab/_circle_variations.scss": 1482699623000,
  "scss/lab/_facebook-network.scss": 1455464726000,
  "scss/lab/_spikes.scss": 1455464726000,
  "scss/notations/_main.scss": 1482699623000,
  "scss/breakpoints/_1030up.scss": 1455464726000,
  "scss/breakpoints/_1240up.scss": 1482699623000,
  "scss/breakpoints/_486up.scss": 1455464726000,
  "scss/breakpoints/_768up.scss": 1455464726000,
  "scss/breakpoints/_base.scss": 1482699623000,
  "scss/partials/_mixins.scss": 1455464726000,
  "scss/partials/_normalize.scss": 1455464726000,
  "scss/partials/_typography.scss": 1482699623000,
  "scss/partials/_variables.scss": 1460620133000,
  "img/.DS_Store": 1477484966000,
  "img/backgrounds/white-paper.jpg": 1455464726000,
  "img/backgrounds/white-paper2.jpg": 1482699622000,
  "img/thumbs/bug-goes-town-200x200.jpg": 1455464726000,
  "img/thumbs/chairy-tale-200x200.jpg": 1455464726000,
  "img/thumbs/canon-200x200.jpg": 1455464726000,
  "img/thumbs/concurrents-200x200.jpg": 1455464726000,
  "img/thumbs/lines-vertical-200x200.jpg": 1455464726000,
  "img/thumbs/notations-for-animation-1200x630.jpg": 1455464726000,
  "img/thumbs/nude.gif": 1455464726000,
  "img/thumbs/panther-200x200.jpg": 1455464726000,
  "img/thumbs/sisisi-200x200.jpg": 1455464726000,
  "img/posters/SiSiSiSiSiSiSiSiSiSiSi-poster.jpg": 1482699622000,
  "img/posters/a-chairy-tale-poster.jpg": 1482699622000,
  "img/posters/bug-goes-to-town-poster.jpg": 1482699622000,
  "img/posters/tango-poster.jpg": 1482699622000,
  "img/lab/binary-rings-large.jpg": 1482699622000,
  "img/lab/binary-rings-thumb.jpg": 1482699622000,
  "img/lab/binary-rings.jpg": 1482699622000,
  "img/lab/bubble-chamber-large.jpg": 1482699622000,
  "img/lab/bubble-chamber-thumb.jpg": 1482699622000,
  "img/lab/bubble-chamber.jpg": 1482699622000,
  "img/lab/circle-variations-large.jpg": 1482699622000,
  "img/lab/circle-variations-thumb.jpg": 1482699622000,
  "img/lab/circle-variations.jpg": 1482699622000,
  "img/lab/defunciones-large.jpg": 1482699622000,
  "img/lab/defunciones-thumb.jpg": 1482699622000,
  "img/lab/defunciones.jpg": 1482699622000,
  "img/lab/empathy-mcdonald-large.jpg": 1482699622000,
  "img/lab/empathy-mcdonald-thumb.jpg": 1482699622000,
  "img/lab/empathy-mcdonald.jpg": 1482699622000,
  "img/lab/fb-network-large.jpg": 1482699622000,
  "img/lab/fb-network-thumb.jpg": 1482699622000,
  "img/lab/fb-network.jpg": 1482699622000,
  "img/lab/feathers-large.jpg": 1482699622000,
  "img/lab/feathers-thumb.jpg": 1482699622000,
  "img/lab/feathers.jpg": 1482699622000,
  "img/lab/flock-a-large.jpg": 1482699622000,
  "img/lab/flock-a-thumb.jpg": 1482699622000,
  "img/lab/flock-a.jpg": 1482699622000,
  "img/lab/flock-b-large.jpg": 1482699622000,
  "img/lab/flock-b-thumb.jpg": 1482699622000,
  "img/lab/flock-b.jpg": 1482699622000,
  "img/lab/flock-large.jpg": 1482699622000,
  "img/lab/flock-thumb.jpg": 1482699622000,
  "img/lab/flock.jpg": 1482699622000,
  "img/lab/guts-large.jpg": 1482699622000,
  "img/lab/guts-thumb.jpg": 1482699622000,
  "img/lab/guts.jpg": 1482699622000,
  "img/lab/monitor-info-large.jpg": 1482699622000,
  "img/lab/monitor-info-thumb.jpg": 1482699622000,
  "img/lab/monitor-info.jpg": 1482699622000,
  "img/lab/now-large.jpg": 1482699622000,
  "img/lab/now-thumb.jpg": 1482699622000,
  "img/lab/now.jpg": 1482699622000,
  "img/lab/perlin-violence-map-large.jpg": 1482699622000,
  "img/lab/perlin-violence-map-thumb.jpg": 1482699622000,
  "img/lab/perlin-violence-map.jpg": 1482699622000,
  "img/lab/pollockShimmering.gif": 1482699622000,
  "img/lab/pulse-analysis-b-large.jpg": 1482699622000,
  "img/lab/pulse-analysis-b-thumb.jpg": 1482699622000,
  "img/lab/pulse-analysis-b.jpg": 1482699622000,
  "img/lab/pulse-analysis-c-large.jpg": 1482699622000,
  "img/lab/pulse-analysis-c-thumb.jpg": 1482699622000,
  "img/lab/pulse-analysis-c.jpg": 1482699622000,
  "img/lab/pulse-analysis-large.jpg": 1482699622000,
  "img/lab/pulse-analysis-thumb.jpg": 1482699622000,
  "img/lab/pulse-analysis.jpg": 1482699622000,
  "img/lab/pulse-waves-large.jpg": 1482699622000,
  "img/lab/pulse-waves-thumb.jpg": 1482699622000,
  "img/lab/pulse-waves.jpg": 1482699622000,
  "img/lab/pulsescape-a-large.jpg": 1482699622000,
  "img/lab/pulsescape-a-thumb.jpg": 1482699622000,
  "img/lab/pulsescape-a.jpg": 1482699622000,
  "img/lab/pulsescape-large.jpg": 1482699622000,
  "img/lab/pulsescape-thumb.jpg": 1482699622000,
  "img/lab/pulsescape.jpg": 1482699622000,
  "img/lab/seismic-paths-large.jpg": 1482699622000,
  "img/lab/seismic-paths-thumb.jpg": 1482699622000,
  "img/lab/seismic-paths.jpg": 1482699622000,
  "img/lab/spikes-large.jpg": 1482699622000,
  "img/lab/spikes-thumb.jpg": 1482699622000,
  "img/lab/spikes.jpg": 1482699622000,
  "img/lab/substrate-large.jpg": 1482699622000,
  "img/lab/substrate-thumb.jpg": 1482699622000,
  "img/lab/substrate.jpg": 1482699622000,
  "img/sprites/.DS_Store": 1460613976000,
  "img/sprites/bird2.png": 1455464726000,
  "img/sprites/birdFly_f5_w226_h50.png": 1455464726000,
  "img/sprites/curiousBird_fh7-fv5_w944-h1111.jpg": 1466677721000,
  "img/sprites/head.png": 1455464726000,
  "img/sprites/ink_f14_w840_h200_offx26_offy197.png": 1455464726000,
  "img/sprites/levit.png": 1455464726000,
  "img/sprites/lines-01-small.png": 1455464726000,
  "img/sprites/numbersFrom0to6_9_col10_row_7_w3050_h1638_offx162_offy176.jpg": 1455464726000,
  "img/sprites/pencil_f4_w80-h60.png": 1455464726000,
  "img/sprites/rotating_triangle.png": 1482699622000,
  "img/sprites/shadows-sprite.png": 1455464726000,
  "img/notations/.DS_Store": 1461149666000,
  "img/notations/CVM_Kreise_34611.jpg": 1482699622000,
  "img/notations/CVMamericanmarch_C.jpg": 1482699622000,
  "img/notations/No.366-166-large.jpg": 1482699622000,
  "img/notations/No.366-166-thumb.jpg": 1482699622000,
  "img/notations/No.366-166.jpg": 1482699622000,
  "img/notations/adk11_NewBook.jpg": 1482699622000,
  "img/notations/bug-goes-to-town.jpg": 1482699622000,
  "img/notations/carne-estructura-large.jpg": 1482699622000,
  "img/notations/carne-estructura-thumb.jpg": 1482699622000,
  "img/notations/carne-estructura.jpg": 1482699622000,
  "img/notations/chairy-tale-large.jpg": 1482699622000,
  "img/notations/chairy-tale-notations.jpg": 1482699622000,
  "img/notations/chairy-tale-small.jpg": 1482699622000,
  "img/notations/chairy-tale-thumb.jpg": 1482699622000,
  "img/notations/chairy-tale.jpg": 1482699622000,
  "img/notations/fleischer-bugGoesToTown-large.jpg": 1482699622000,
  "img/notations/fleischer-bugGoesToTown-thumb.jpg": 1482699622000,
  "img/notations/fleischer-bugGoesToTown.jpg": 1482699622000,
  "img/notations/pantera sonido-large.jpg": 1482699622000,
  "img/notations/pantera sonido-thumb.jpg": 1482699622000,
  "img/notations/pantera sonido.jpg": 1482699622000,
  "img/notations/pantera-large.jpg": 1482699622000,
  "img/notations/pantera-thumb.jpg": 1482699622000,
  "img/notations/pantera.jpg": 1482699622000,
  "img/notations/panthera1-large.jpg": 1482699622000,
  "img/notations/panthera1-thumb.jpg": 1482699622000,
  "img/notations/panthera1.jpg": 1482699622000,
  "img/notations/pantheras-large.jpg": 1482699622000,
  "img/notations/pantheras-thumb.jpg": 1482699622000,
  "img/notations/pantheras.jpg": 1482699622000,
  "img/notations/sisisi-estructura-large.jpg": 1482699622000,
  "img/notations/sisisi-estructura-thumb.jpg": 1482699622000,
  "img/notations/sisisi-estructura.jpg": 1482699622000,
  "img/notations/sisisi-final-map-large.jpg": 1482699622000,
  "img/notations/sisisi-final-map-thumb.jpg": 1482699622000,
  "img/notations/sisisi-final-map.jpg": 1482699622000,
  "img/notations/sisisi-final-zoom-large.jpg": 1482699622000,
  "img/notations/sisisi-final-zoom-thumb.jpg": 1482699622000,
  "img/notations/sisisi-final-zoom.jpg": 1482699622000,
  "img/notations/sisisi-first-map-large.jpg": 1482699622000,
  "img/notations/sisisi-first-map-thumb.jpg": 1482699622000,
  "img/notations/sisisi-first-map.jpg": 1482699622000,
  "img/notations/sisisi-large.jpg": 1482699622000,
  "img/notations/sisisi-notations.jpg": 1482699622000,
  "img/notations/sisisi-second-map-large.jpg": 1482699622000,
  "img/notations/sisisi-second-map-thumb.jpg": 1482699622000,
  "img/notations/sisisi-second-map.jpg": 1482699622000,
  "img/notations/sisisi-thumb.jpg": 1482699622000,
  "img/notations/sisisi.jpg": 1482699622000,
  "img/notations/tango-large.jpg": 1482699622000,
  "img/notations/tango-small.jpg": 1482699622000,
  "img/notations/tango-thumb.jpg": 1482699622000,
  "img/notations/tango.jpg": 1482699622000,
  "img/notations/tango/tango0.jpg": 1482699622000,
  "img/notations/tango/tango11.jpg": 1482699622000,
  "img/notations/tango/tango1.jpg": 1482699622000,
  "img/notations/tango/tango10.jpg": 1482699622000,
  "img/notations/tango/tango12.jpg": 1482699622000,
  "img/notations/tango/tango13.jpg": 1482699622000,
  "img/notations/tango/tango14.jpg": 1482699622000,
  "img/notations/tango/tango15.jpg": 1482699622000,
  "img/notations/tango/tango2.jpg": 1482699622000,
  "img/notations/tango/tango3.jpg": 1482699622000,
  "img/notations/tango/tango4.jpg": 1482699622000,
  "img/notations/tango/tango5.jpg": 1482699622000,
  "img/notations/tango/tango6.jpg": 1482699622000,
  "img/notations/tango/tango7.jpg": 1482699622000,
  "img/notations/tango/tango8.jpg": 1482699622000,
  "img/notations/tango/tango9.jpg": 1482699622000,
  "lab/.DS_Store": 1480094219000,
  "lab/index.md": 1482699623000,
  "lab/_TEMPLATE/index.md": 1482699622000,
  "lab/_TEMPLATE/js/scripts.js": 1482699622000,
  "lab/bubble-chamber-jared-tarbell/index.md": 1482699622000,
  "lab/bubble-chamber-jared-tarbell/img/bubble-chamber.jpg": 1482699622000,
  "lab/bubble-chamber-jared-tarbell/js/scripts.js": 1482699622000,
  "lab/defunciones-b/index.md": 1482705964000,
  "lab/defunciones-b/js/scripts.js": 1482704001000,
  "lab/defunciones/index.md": 1482699622000,
  "lab/defunciones/img/defunciones.jpg": 1482699622000,
  "lab/defunciones/js/scripts.js": 1482699622000,
  "lab/binary-ring-jared-tarbell/.DS_Store": 1480096049000,
  "lab/binary-ring-jared-tarbell/index.md": 1482699622000,
  "lab/binary-ring-jared-tarbell/img/binary-rings.jpg": 1482699622000,
  "lab/binary-ring-jared-tarbell/js/scripts.js": 1482699622000,
  "lab/circle-variations/.DS_Store": 1461140745000,
  "lab/circle-variations/index.md": 1482699622000,
  "lab/circle-variations/img/circle-variations.jpg": 1482699622000,
  "lab/circle-variations/js/scripts.js": 1482699622000,
  "lab/earthquakes-path/.DS_Store": 1460954074000,
  "lab/earthquakes-path/index.md": 1482699622000,
  "lab/earthquakes-path/js/scripts.js": 1482699622000,
  "lab/earthquakes-path/img/seismic-paths.jpg": 1482699622000,
  "lab/empathy-kyle-mcdonald/index.md": 1482699623000,
  "lab/empathy-kyle-mcdonald/img/empathy-mcdonald.jpg": 1482699623000,
  "lab/empathy-kyle-mcdonald/js/scripts.js": 1482706670000,
  "lab/facebook-network/index.md": 1482699623000,
  "lab/facebook-network/img/fb-network.jpg": 1482699623000,
  "lab/facebook-network/js/scripts.js": 1482699623000,
  "lab/flock/index.md": 1482699623000,
  "lab/flock/img/flock.jpg": 1482699623000,
  "lab/flock/js/scripts.js": 1482699623000,
  "lab/flock-a/index.md": 1482699623000,
  "lab/flock-a/js/scripts.js": 1482699623000,
  "lab/flock-a/img/flock-a.jpg": 1482699623000,
  "lab/flock-b/index.md": 1482699623000,
  "lab/flock-b/img/flock-b.jpg": 1482699623000,
  "lab/flock-b/js/scripts.js": 1482699623000,
  "lab/perlin-violence-map/index.md": 1482699623000,
  "lab/perlin-violence-map/img/perlin-violence-map.jpg": 1482699623000,
  "lab/perlin-violence-map/js/scripts.js": 1482699623000,
  "lab/now-loop/index.md": 1482699623000,
  "lab/now-loop/img/now.jpg": 1482699623000,
  "lab/now-loop/js/scripts.js": 1482699623000,
  "lab/monitor-info/index.md": 1482699623000,
  "lab/monitor-info/img/monitor-info.jpg": 1482699623000,
  "lab/monitor-info/js/scripts.js": 1482699623000,
  "lab/guts-jared-tarbell/.DS_Store": 1480094213000,
  "lab/guts-jared-tarbell/index.md": 1482699623000,
  "lab/guts-jared-tarbell/js/scripts.js": 1482699623000,
  "lab/guts-jared-tarbell/img/guts.jpg": 1482699623000,
  "lab/pulse-analysis/.DS_Store": 1456473732000,
  "lab/pulse-analysis/index.md": 1482699623000,
  "lab/pulse-analysis/js/scripts.js": 1482699623000,
  "lab/pulse-analysis/img/pulse-analysis.jpg": 1482699623000,
  "lab/pulse-analysis-b/index.md": 1482699623000,
  "lab/pulse-analysis-b/img/pulse-analysis-b.jpg": 1482699623000,
  "lab/pulse-analysis-b/js/scripts.js": 1482699623000,
  "lab/pulsescape/index.md": 1482699623000,
  "lab/pulsescape/img/pulsescape.jpg": 1482699623000,
  "lab/pulsescape/js/scripts.js": 1482699623000,
  "lab/pulsescape-a/index.md": 1482699623000,
  "lab/pulsescape-a/img/pulsescape-a.jpg": 1482699623000,
  "lab/pulsescape-a/js/scripts.js": 1482699623000,
  "lab/pulse-analysis-c/index.md": 1482699623000,
  "lab/pulse-analysis-c/img/pulse-analysis-c.jpg": 1482699623000,
  "lab/pulse-analysis-c/js/scripts.js": 1482699623000,
  "lab/pulsescape-waves/index.md": 1482699623000,
  "lab/pulsescape-waves/img/pulse-waves.jpg": 1482699623000,
  "lab/pulsescape-waves/js/scripts.js": 1482699623000,
  "lab/substrate-watercolor-jared-tarbell/.DS_Store": 1480093768000,
  "lab/substrate-watercolor-jared-tarbell/index.md": 1482699623000,
  "lab/substrate-watercolor-jared-tarbell/img/substrate.jpg": 1482699623000,
  "lab/substrate-watercolor-jared-tarbell/js/scripts.js": 1482699623000,
  "lab/tireless-feathers/.DS_Store": 1461139568000,
  "lab/tireless-feathers/index.md": 1482699623000,
  "lab/tireless-feathers/js/scripts.js": 1482699623000,
  "lab/tireless-feathers/img/feathers.jpg": 1482699623000,
  "lab/spikes/index.md": 1482699623000,
  "lab/spikes/img/spikes.jpg": 1482699623000,
  "lab/spikes/js/scripts.js": 1482699623000,
  "notations/.DS_Store": 1461149476000,
  "notations/index.md": 1482699623000,
  "notations/01/.DS_Store": 1461136497000,
  "notations/01/index.md": 1482699623000,
  "notations/01/img/.DS_Store": 1461136721000,
  "notations/01/img/No.366-166.jpg": 1482699623000,
  "notations/a-chairy-tale/index.md": 1482699623000,
  "notations/a-chairy-tale/img/chairy-tale.jpg": 1482699623000,
  "notations/a-chairy-tale/js/scripts.js": 1482699623000,
  "notations/mr-bug-goes-to-town/index.md": 1482699623000,
  "notations/mr-bug-goes-to-town/js/scripts.js": 1482699623000,
  "notations/mr-bug-goes-to-town/img/fleischer-bugGoesToTown.jpg": 1482699623000,
  "notations/carne/.DS_Store": 1461149471000,
  "notations/carne/index.md": 1482699623000,
  "notations/carne/img/.DS_Store": 1461162816000,
  "notations/carne/img/carne-estructura.jpg": 1482699623000,
  "notations/panther/.DS_Store": 1461056731000,
  "notations/panther/index.md": 1482699623000,
  "notations/panther/img/.DS_Store": 1461066471000,
  "notations/panther/img/pantera sonido.jpg": 1482699623000,
  "notations/panther/img/pantera.jpg": 1482699623000,
  "notations/panther/img/panthera1.jpg": 1482699623000,
  "notations/panther/img/pantheras.jpg": 1482699623000,
  "notations/sisisisisisisisisisisi/index.md": 1482699623000,
  "notations/sisisisisisisisisisisi/img/sisisi-estructura.jpg": 1482699623000,
  "notations/sisisisisisisisisisisi/img/sisisi-final-map.jpg": 1482699623000,
  "notations/sisisisisisisisisisisi/img/sisisi-final-zoom.jpg": 1482699623000,
  "notations/sisisisisisisisisisisi/img/sisisi-first-map.jpg": 1482699623000,
  "notations/sisisisisisisisisisisi/img/sisisi-second-map.jpg": 1482699623000,
  "notations/sisisisisisisisisisisi/img/sisisi.jpg": 1482699623000,
  "notations/sisisisisisisisisisisi/js/scripts.js": 1482699623000,
  "notations/tango/.DS_Store": 1460954079000,
  "notations/tango/index.md": 1482699623000,
  "notations/tango/img/tango.jpg": 1482699623000,
  "notations/tango/js/.DS_Store": 1460954039000,
  "notations/tango/js/scripts.js": 1482699623000
}